{
"taskDefinition": {
    "volumes": [],
    "taskDefinitionArn": "arn:aws:ecs:us-east-1:713150122548:task-definition/first-run-task-definition:4",
    "containerDefinitions": [
        {
            "name": "ecr-ecs",
            "image": "{{image}}",
            "cpu": 10,
            "portMappings": [
                {
                    "containerPort": 80,
                    "hostPort": 80
                }
            ],
            "memory": 256,
            "essential": true
        }
    ],
    "family": "first-run-task-definition",
    "revision": 4
}
}

